tablevault/__init__.py
tablevault/cli.py
tablevault/core.py
tablevault/_builders/__init__.py
tablevault/_builders/base_builder_type.py
tablevault/_builders/builder_constants.py
tablevault/_builders/column_builder_type.py
tablevault/_builders/index_builder_type.py
tablevault/_builders/load_builder.py
tablevault/_builders/examples/__init__.py
tablevault/_builders/examples/base_builder.yaml
tablevault/_builders/examples/column_builder.yaml
tablevault/_builders/examples/index_builder.yaml
tablevault/_builders/examples/mapping.py
tablevault/_dataframe_helper/__init__.py
tablevault/_dataframe_helper/artifact.py
tablevault/_dataframe_helper/table_operations.py
tablevault/_defintions/__init__.py
tablevault/_defintions/constants.py
tablevault/_defintions/tv_errors.py
tablevault/_defintions/types.py
tablevault/_helper/__init__.py
tablevault/_helper/copy_write_file.py
tablevault/_helper/database_lock.py
tablevault/_helper/external_drive_check.py
tablevault/_helper/file_operations.py
tablevault/_helper/metadata_store.py
tablevault/_helper/user_lock.py
tablevault/_helper/utils.py
tablevault/_helper/examples/__init__.py
tablevault/_helper/examples/example.py
tablevault/_operations/__init__.py
tablevault/_operations/_get_operations.py
tablevault/_operations/_meta_operations.py
tablevault/_operations/_setup_operations.py
tablevault/_operations/_table_execution.py
tablevault/_operations/_takedown_operations.py
tablevault/_operations/_vault_operations.py
tablevault/_remote_helper/__init__.py
tablevault/_remote_helper/_remote_save_helper.py
tablevault/_remote_helper/remote_save_process.py
tablevault/_table_reference/table_reference.py
tablevault/code_functions/random_string.py
tablevault/code_functions/table_generation.py
tablevault-0.1.1.dist-info/licenses/LICENSE
tablevault-0.1.1.dist-info/METADATA
tablevault-0.1.1.dist-info/WHEEL
tablevault-0.1.1.dist-info/entry_points.txt
tablevault-0.1.1.dist-info/top_level.txt
tablevault-0.1.1.dist-info/RECORD
