Metadata-Version: 2.4
Name: tablevault
Version: 0.1.1
Summary: Dataframe and File Transformation Execution and Versioning Tool.
Author-email: Jinjin Zhao <j2zhao@uchicago.edu>
License: BSD 3-Clause License
Keywords: example,package,python
Requires-Python: >=3.11
License-File: LICENSE
Requires-Dist: numpy
Requires-Dist: pandas
Requires-Dist: filelock
Requires-Dist: pyyaml
Requires-Dist: dataclasses_json
Requires-Dist: psutil
Requires-Dist: pydantic
Requires-Dist: click
Requires-Dist: rich
Provides-Extra: dev
Requires-Dist: ruff; extra == "dev"
Requires-Dist: pytest; extra == "dev"
Requires-Dist: mkdocs-material; extra == "dev"
Requires-Dist: mike; extra == "dev"
Dynamic: license-file
